axelsolver
