Metadata-Version: 2.1
Name: axelsolver
Version: 0.0.3
Summary: AxelSolver are a series of Solvers (classes) that run specific tasks, for example: VoiceSolver is for Text-to-Speech and NuclearSolver is for a KillSwitch website (just in case AI takes over.)
Author: NullDev (Naiel V)
